{
  "meta": {
    "recorderName": "sempat_panick",
    "playerName": "sempat_panick",
    "avatarProfile": {
      "bodyDepthScale": 1,
      "bodyHeightScale": 1,
      "bodyTypeScale": 1,
      "bodyWidthScale": 1,
      "capturedAtUtc": "2026-04-27T00:25:32Z",
      "headScale": 1,
      "hipHeight": 5.077,
      "jumpHeight": 7.2,
      "jumpPower": 50,
      "rigType": "Enum.HumanoidRigType.R15",
      "rootPartSize": {
        "x": 2,
        "y": 2,
        "z": 1
      },
      "rootToFeetHeight": 6.077,
      "walkSpeed": 29
    },
    "totalEvents": 197,
    "durationSeconds": 9.834,
    "startedAtUtc": "2026-04-27T00:25:32Z",
    "gameId": 8644306226,
    "placeId": 76964310785698,
    "jobId": "f7dfafff-a43a-44e0-95d0-b2ee686f5ac9"
  },
  "events": [
    {
      "t": 0,
      "kind": "key_down",
      "data": {
        "gameProcessed": false,
        "keyCode": "Enum.KeyCode.W"
      }
    },
    {
      "t": 0.017,
      "kind": "movement",
      "data": {
        "isGrounded": true,
        "walkSpeed": 29,
        "jumpHeight": 7.2,
        "jumpPower": 50,
        "position": {
          "x": -434.994,
          "y": 250.122,
          "z": 717.196
        },
        "lookDirection": {
          "x": -0.069,
          "y": 0,
          "z": -0.998
        },
        "moveDirection": {
          "x": -0.148,
          "y": 0,
          "z": -0.989
        },
        "velocity": {
          "x": -1.157,
          "y": 0,
          "z": -7.776
        }
      }
    },
    {
      "t": 0.132,
      "kind": "movement",
      "data": {
        "isGrounded": true,
        "walkSpeed": 29,
        "jumpHeight": 7.2,
        "jumpPower": 50,
        "position": {
          "x": -435.43,
          "y": 250.122,
          "z": 714.28
        },
        "lookDirection": {
          "x": -0.121,
          "y": 0,
          "z": -0.993
        },
        "moveDirection": {
          "x": -0.148,
          "y": 0,
          "z": -0.989
        },
        "velocity": {
          "x": -4.272,
          "y": 0,
          "z": -28.683
        }
      }
    },
    {
      "t": 0.184,
      "kind": "key_down",
      "data": {
        "gameProcessed": false,
        "keyCode": "Enum.KeyCode.Space"
      }
    },
    {
      "t": 0.186,
      "kind": "jump_request",
      "data": []
    },
    {
      "t": 0.199,
      "kind": "humanoid_state",
      "data": {
        "state": "Enum.HumanoidStateType.Jumping"
      }
    },
    {
      "t": 0.202,
      "kind": "jump_request",
      "data": []
    },
    {
      "t": 0.216,
      "kind": "humanoid_state",
      "data": {
        "state": "Enum.HumanoidStateType.Freefall"
      }
    },
    {
      "t": 0.219,
      "kind": "jump_request",
      "data": []
    },
    {
      "t": 0.234,
      "kind": "movement",
      "data": {
        "isGrounded": true,
        "walkSpeed": 29,
        "jumpHeight": 7.2,
        "jumpPower": 50,
        "position": {
          "x": -435.898,
          "y": 252.593,
          "z": 711.296
        },
        "lookDirection": {
          "x": -0.142,
          "y": 0,
          "z": -0.99
        },
        "moveDirection": {
          "x": -0.156,
          "y": 0,
          "z": -0.988
        },
        "velocity": {
          "x": -4.537,
          "y": 44.978,
          "z": -28.643
        }
      }
    },
    {
      "t": 0.251,
      "kind": "key_up",
      "data": {
        "gameProcessed": false,
        "keyCode": "Enum.KeyCode.Space"
      }
    },
    {
      "t": 0.349,
      "kind": "movement",
      "data": {
        "isGrounded": false,
        "walkSpeed": 29,
        "jumpHeight": 7.2,
        "jumpPower": 50,
        "position": {
          "x": -436.409,
          "y": 256.365,
          "z": 708.074
        },
        "lookDirection": {
          "x": -0.151,
          "y": 0,
          "z": -0.988
        },
        "moveDirection": {
          "x": -0.156,
          "y": 0,
          "z": -0.988
        },
        "velocity": {
          "x": -4.537,
          "y": 22.906,
          "z": -28.643
        }
      }
    },
    {
      "t": 0.45,
      "kind": "movement",
      "data": {
        "isGrounded": false,
        "walkSpeed": 29,
        "jumpHeight": 7.2,
        "jumpPower": 50,
        "position": {
          "x": -436.842,
          "y": 257.644,
          "z": 705.085
        },
        "lookDirection": {
          "x": -0.145,
          "y": 0,
          "z": -0.989
        },
        "moveDirection": {
          "x": -0.105,
          "y": 0,
          "z": -0.995
        },
        "velocity": {
          "x": -3.046,
          "y": 2.468,
          "z": -28.839
        }
      }
    },
    {
      "t": 0.55,
      "kind": "movement",
      "data": {
        "isGrounded": false,
        "walkSpeed": 29,
        "jumpHeight": 7.2,
        "jumpPower": 50,
        "position": {
          "x": -436.984,
          "y": 256.94,
          "z": 702.31
        },
        "lookDirection": {
          "x": -0.091,
          "y": 0,
          "z": -0.996
        },
        "moveDirection": {
          "x": -0.035,
          "y": 0,
          "z": -0.999
        },
        "velocity": {
          "x": -1.017,
          "y": -16.334,
          "z": -28.982
        }
      }
    },
    {
      "t": 0.649,
      "kind": "humanoid_state",
      "data": {
        "state": "Enum.HumanoidStateType.Landed"
      }
    },
    {
      "t": 0.65,
      "kind": "movement",
      "data": {
        "isGrounded": true,
        "walkSpeed": 29,
        "jumpHeight": 7.2,
        "jumpPower": 50,
        "position": {
          "x": -436.704,
          "y": 254.285,
          "z": 699.434
        },
        "lookDirection": {
          "x": 0.03,
          "y": 0,
          "z": -1
        },
        "moveDirection": {
          "x": 0.25,
          "y": 0,
          "z": -0.968
        },
        "velocity": {
          "x": 7.072,
          "y": -35.954,
          "z": -28.095
        }
      }
    },
    {
      "t": 0.75,
      "kind": "key_down",
      "data": {
        "gameProcessed": false,
        "keyCode": "Enum.KeyCode.Space"
      }
    },
    {
      "t": 0.752,
      "kind": "jump_request",
      "data": []
    },
    {
      "t": 0.767,
      "kind": "humanoid_state",
      "data": {
        "state": "Enum.HumanoidStateType.Jumping"
      }
    },
    {
      "t": 0.768,
      "kind": "movement",
      "data": {
        "isGrounded": true,
        "walkSpeed": 29,
        "jumpHeight": 7.2,
        "jumpPower": 50,
        "position": {
          "x": -435.31,
          "y": 255.15,
          "z": 696.809
        },
        "lookDirection": {
          "x": 0.359,
          "y": 0,
          "z": -0.933
        },
        "moveDirection": {
          "x": 0.737,
          "y": 0,
          "z": -0.676
        },
        "velocity": {
          "x": 14.241,
          "y": 53.154,
          "z": -17.913
        }
      }
    },
    {
      "t": 0.77,
      "kind": "jump_request",
      "data": []
    },
    {
      "t": 0.817,
      "kind": "humanoid_state",
      "data": {
        "state": "Enum.HumanoidStateType.Freefall"
      }
    },
    {
      "t": 0.819,
      "kind": "jump_request",
      "data": []
    },
    {
      "t": 0.85,
      "kind": "key_up",
      "data": {
        "gameProcessed": false,
        "keyCode": "Enum.KeyCode.Space"
      }
    },
    {
      "t": 0.883,
      "kind": "movement",
      "data": {
        "isGrounded": false,
        "walkSpeed": 29,
        "jumpHeight": 7.2,
        "jumpPower": 50,
        "position": {
          "x": -433.286,
          "y": 260.415,
          "z": 695.145
        },
        "lookDirection": {
          "x": 0.805,
          "y": 0,
          "z": -0.593
        },
        "moveDirection": {
          "x": 0.99,
          "y": 0,
          "z": -0.139
        },
        "velocity": {
          "x": 23.036,
          "y": 36.805,
          "z": -9.93
        }
      }
    },
    {
      "t": 1,
      "kind": "movement",
      "data": {
        "isGrounded": false,
        "walkSpeed": 29,
        "jumpHeight": 7.2,
        "jumpPower": 50,
        "position": {
          "x": -430.079,
          "y": 263.326,
          "z": 694.532
        },
        "lookDirection": {
          "x": 0.952,
          "y": 0,
          "z": -0.305
        },
        "moveDirection": {
          "x": 0.99,
          "y": 0,
          "z": -0.139
        },
        "velocity": {
          "x": 28.718,
          "y": 13.915,
          "z": -4.036
        }
      }
    },
    {
      "t": 1.099,
      "kind": "humanoid_state",
      "data": {
        "state": "Enum.HumanoidStateType.Landed"
      }
    },
    {
      "t": 1.1,
      "kind": "movement",
      "data": {
        "isGrounded": true,
        "walkSpeed": 29,
        "jumpHeight": 7.2,
        "jumpPower": 50,
        "position": {
          "x": -427.216,
          "y": 263.78,
          "z": 694.134
        },
        "lookDirection": {
          "x": 0.978,
          "y": 0,
          "z": -0.206
        },
        "moveDirection": {
          "x": 0.99,
          "y": 0,
          "z": -0.139
        },
        "velocity": {
          "x": 27.772,
          "y": 3.553,
          "z": -3.938
        }
      }
    },
    {
      "t": 1.2,
      "kind": "movement",
      "data": {
        "isGrounded": true,
        "walkSpeed": 29,
        "jumpHeight": 7.2,
        "jumpPower": 50,
        "position": {
          "x": -424.875,
          "y": 264.462,
          "z": 693.655
        },
        "lookDirection": {
          "x": 0.978,
          "y": 0,
          "z": -0.207
        },
        "moveDirection": {
          "x": 0.959,
          "y": 0,
          "z": -0.284
        },
        "velocity": {
          "x": 26.937,
          "y": -11.863,
          "z": -7.89
        }
      }
    },
    {
      "t": 1.235,
      "kind": "key_down",
      "data": {
        "gameProcessed": false,
        "keyCode": "Enum.KeyCode.Space"
      }
    },
    {
      "t": 1.24,
      "kind": "jump_request",
      "data": []
    },
    {
      "t": 1.251,
      "kind": "humanoid_state",
      "data": {
        "state": "Enum.HumanoidStateType.Jumping"
      }
    },
    {
      "t": 1.257,
      "kind": "jump_request",
      "data": []
    },
    {
      "t": 1.283,
      "kind": "humanoid_state",
      "data": {
        "state": "Enum.HumanoidStateType.Freefall"
      }
    },
    {
      "t": 1.287,
      "kind": "jump_request",
      "data": []
    },
    {
      "t": 1.3,
      "kind": "movement",
      "data": {
        "isGrounded": false,
        "walkSpeed": 29,
        "jumpHeight": 7.2,
        "jumpPower": 50,
        "position": {
          "x": -422.72,
          "y": 267.854,
          "z": 692.769
        },
        "lookDirection": {
          "x": 0.941,
          "y": 0,
          "z": -0.339
        },
        "moveDirection": {
          "x": 0.866,
          "y": 0,
          "z": -0.5
        },
        "velocity": {
          "x": 22.603,
          "y": 46.614,
          "z": -11.516
        }
      }
    },
    {
      "t": 1.319,
      "kind": "key_up",
      "data": {
        "gameProcessed": false,
        "keyCode": "Enum.KeyCode.Space"
      }
    },
    {
      "t": 1.416,
      "kind": "movement",
      "data": {
        "isGrounded": false,
        "walkSpeed": 29,
        "jumpHeight": 7.2,
        "jumpPower": 50,
        "position": {
          "x": -419.967,
          "y": 271.81,
          "z": 691.106
        },
        "lookDirection": {
          "x": 0.889,
          "y": 0,
          "z": -0.458
        },
        "moveDirection": {
          "x": 0.853,
          "y": 0,
          "z": -0.523
        },
        "velocity": {
          "x": 24.727,
          "y": 24.541,
          "z": -15.153
        }
      }
    },
    {
      "t": 1.53,
      "kind": "movement",
      "data": {
        "isGrounded": true,
        "walkSpeed": 29,
        "jumpHeight": 7.2,
        "jumpPower": 50,
        "position": {
          "x": -417.054,
          "y": 273.29,
          "z": 689.386
        },
        "lookDirection": {
          "x": 0.872,
          "y": 0,
          "z": -0.49
        },
        "moveDirection": {
          "x": 0.87,
          "y": 0,
          "z": -0.492
        },
        "velocity": {
          "x": 25.238,
          "y": 1.651,
          "z": -14.285
        }
      }
    },
    {
      "t": 1.567,
      "kind": "humanoid_state",
      "data": {
        "state": "Enum.HumanoidStateType.Landed"
      }
    },
    {
      "t": 1.633,
      "kind": "movement",
      "data": {
        "isGrounded": true,
        "walkSpeed": 29,
        "jumpHeight": 7.2,
        "jumpPower": 50,
        "position": {
          "x": -414.43,
          "y": 274.507,
          "z": 688.16
        },
        "lookDirection": {
          "x": 0.893,
          "y": 0,
          "z": -0.449
        },
        "moveDirection": {
          "x": 0.921,
          "y": 0,
          "z": -0.391
        },
        "velocity": {
          "x": 26.676,
          "y": 5.395,
          "z": -11.364
        }
      }
    },
    {
      "t": 1.7,
      "kind": "key_down",
      "data": {
        "gameProcessed": false,
        "keyCode": "Enum.KeyCode.Space"
      }
    },
    {
      "t": 1.702,
      "kind": "jump_request",
      "data": []
    },
    {
      "t": 1.716,
      "kind": "humanoid_state",
      "data": {
        "state": "Enum.HumanoidStateType.Jumping"
      }
    },
    {
      "t": 1.719,
      "kind": "jump_request",
      "data": []
    },
    {
      "t": 1.733,
      "kind": "humanoid_state",
      "data": {
        "state": "Enum.HumanoidStateType.Freefall"
      }
    },
    {
      "t": 1.734,
      "kind": "movement",
      "data": {
        "isGrounded": false,
        "walkSpeed": 29,
        "jumpHeight": 7.2,
        "jumpPower": 50,
        "position": {
          "x": -411.728,
          "y": 276.062,
          "z": 687.114
        },
        "lookDirection": {
          "x": 0.921,
          "y": 0,
          "z": -0.389
        },
        "moveDirection": {
          "x": 0.959,
          "y": 0,
          "z": -0.284
        },
        "velocity": {
          "x": 27.711,
          "y": 49.883,
          "z": -8.511
        }
      }
    },
    {
      "t": 1.735,
      "kind": "jump_request",
      "data": []
    },
    {
      "t": 1.816,
      "kind": "key_up",
      "data": {
        "gameProcessed": false,
        "keyCode": "Enum.KeyCode.Space"
      }
    },
    {
      "t": 1.849,
      "kind": "movement",
      "data": {
        "isGrounded": false,
        "walkSpeed": 29,
        "jumpHeight": 7.2,
        "jumpPower": 50,
        "position": {
          "x": -408.422,
          "y": 280.498,
          "z": 686.396
        },
        "lookDirection": {
          "x": 0.962,
          "y": 0,
          "z": -0.274
        },
        "moveDirection": {
          "x": 0.98,
          "y": 0,
          "z": -0.199
        },
        "velocity": {
          "x": 28.418,
          "y": 26.993,
          "z": -5.782
        }
      }
    },
    {
      "t": 1.95,
      "kind": "movement",
      "data": {
        "isGrounded": false,
        "walkSpeed": 29,
        "jumpHeight": 7.2,
        "jumpPower": 50,
        "position": {
          "x": -405.578,
          "y": 282.302,
          "z": 685.911
        },
        "lookDirection": {
          "x": 0.977,
          "y": 0,
          "z": -0.214
        },
        "moveDirection": {
          "x": 0.993,
          "y": 0,
          "z": -0.122
        },
        "velocity": {
          "x": 26.947,
          "y": 19.748,
          "z": -3.793
        }
      }
    },
    {
      "t": 2.067,
      "kind": "movement",
      "data": {
        "isGrounded": true,
        "walkSpeed": 29,
        "jumpHeight": 7.2,
        "jumpPower": 50,
        "position": {
          "x": -402.246,
          "y": 285.508,
          "z": 685.697
        },
        "lookDirection": {
          "x": 0.993,
          "y": 0,
          "z": -0.116
        },
        "moveDirection": {
          "x": 1,
          "y": 0,
          "z": -0.017
        },
        "velocity": {
          "x": 28.989,
          "y": 3.424,
          "z": -0.561
        }
      }
    },
    {
      "t": 2.183,
      "kind": "movement",
      "data": {
        "isGrounded": true,
        "walkSpeed": 29,
        "jumpHeight": 7.2,
        "jumpPower": 50,
        "position": {
          "x": -399.014,
          "y": 285.566,
          "z": 685.756
        },
        "lookDirection": {
          "x": 1,
          "y": 0,
          "z": -0.029
        },
        "moveDirection": {
          "x": 1,
          "y": 0,
          "z": 0.026
        },
        "velocity": {
          "x": 28.246,
          "y": 2.687,
          "z": 0.71
        }
      }
    },
    {
      "t": 2.251,
      "kind": "key_down",
      "data": {
        "gameProcessed": false,
        "keyCode": "Enum.KeyCode.Space"
      }
    },
    {
      "t": 2.253,
      "kind": "jump_request",
      "data": []
    },
    {
      "t": 2.266,
      "kind": "humanoid_state",
      "data": {
        "state": "Enum.HumanoidStateType.Jumping"
      }
    },
    {
      "t": 2.268,
      "kind": "jump_request",
      "data": []
    },
    {
      "t": 2.283,
      "kind": "humanoid_state",
      "data": {
        "state": "Enum.HumanoidStateType.Freefall"
      }
    },
    {
      "t": 2.284,
      "kind": "movement",
      "data": {
        "isGrounded": true,
        "walkSpeed": 29,
        "jumpHeight": 7.2,
        "jumpPower": 50,
        "position": {
          "x": -396.705,
          "y": 287.514,
          "z": 685.814
        },
        "lookDirection": {
          "x": 1,
          "y": 0,
          "z": 0.002
        },
        "moveDirection": {
          "x": 1,
          "y": 0,
          "z": 0
        },
        "velocity": {
          "x": 22.937,
          "y": 47.431,
          "z": 0.375
        }
      }
    },
    {
      "t": 2.285,
      "kind": "jump_request",
      "data": []
    },
    {
      "t": 2.351,
      "kind": "key_up",
      "data": {
        "gameProcessed": false,
        "keyCode": "Enum.KeyCode.Space"
      }
    },
    {
      "t": 2.4,
      "kind": "movement",
      "data": {
        "isGrounded": false,
        "walkSpeed": 29,
        "jumpHeight": 7.2,
        "jumpPower": 50,
        "position": {
          "x": -393.324,
          "y": 291.763,
          "z": 685.684
        },
        "lookDirection": {
          "x": 1,
          "y": 0,
          "z": -0.029
        },
        "moveDirection": {
          "x": 0.999,
          "y": 0,
          "z": -0.052
        },
        "velocity": {
          "x": 28.96,
          "y": 23.723,
          "z": -1.518
        }
      }
    },
    {
      "t": 2.516,
      "kind": "movement",
      "data": {
        "isGrounded": false,
        "walkSpeed": 29,
        "jumpHeight": 7.2,
        "jumpPower": 50,
        "position": {
          "x": -389.945,
          "y": 293.148,
          "z": 685.505
        },
        "lookDirection": {
          "x": 0.999,
          "y": 0,
          "z": -0.044
        },
        "moveDirection": {
          "x": 0.999,
          "y": 0,
          "z": -0.052
        },
        "velocity": {
          "x": 28.96,
          "y": 0.833,
          "z": -1.518
        }
      }
    },
    {
      "t": 2.617,
      "kind": "movement",
      "data": {
        "isGrounded": false,
        "walkSpeed": 29,
        "jumpHeight": 7.2,
        "jumpPower": 50,
        "position": {
          "x": -387.047,
          "y": 292.21,
          "z": 685.403
        },
        "lookDirection": {
          "x": 0.999,
          "y": 0,
          "z": -0.039
        },
        "moveDirection": {
          "x": 1,
          "y": 0,
          "z": -0.026
        },
        "velocity": {
          "x": 28.99,
          "y": -18.787,
          "z": -0.759
        }
      }
    },
    {
      "t": 2.667,
      "kind": "humanoid_state",
      "data": {
        "state": "Enum.HumanoidStateType.Landed"
      }
    },
    {
      "t": 2.717,
      "kind": "movement",
      "data": {
        "isGrounded": true,
        "walkSpeed": 29,
        "jumpHeight": 7.2,
        "jumpPower": 50,
        "position": {
          "x": -384.269,
          "y": 290.909,
          "z": 685.334
        },
        "lookDirection": {
          "x": 1,
          "y": 0,
          "z": -0.031
        },
        "moveDirection": {
          "x": 1,
          "y": 0,
          "z": -0.017
        },
        "velocity": {
          "x": 28.986,
          "y": -18.42,
          "z": -0.516
        }
      }
    },
    {
      "t": 2.833,
      "kind": "movement",
      "data": {
        "isGrounded": true,
        "walkSpeed": 29,
        "jumpHeight": 7.2,
        "jumpPower": 50,
        "position": {
          "x": -380.888,
          "y": 288.886,
          "z": 685.304
        },
        "lookDirection": {
          "x": 1,
          "y": 0,
          "z": -0.017
        },
        "moveDirection": {
          "x": 1,
          "y": 0,
          "z": -0.009
        },
        "velocity": {
          "x": 29.003,
          "y": -14.41,
          "z": -0.213
        }
      }
    },
    {
      "t": 2.868,
      "kind": "key_down",
      "data": {
        "gameProcessed": false,
        "keyCode": "Enum.KeyCode.Space"
      }
    },
    {
      "t": 2.87,
      "kind": "jump_request",
      "data": []
    },
    {
      "t": 2.883,
      "kind": "humanoid_state",
      "data": {
        "state": "Enum.HumanoidStateType.Jumping"
      }
    },
    {
      "t": 2.886,
      "kind": "jump_request",
      "data": []
    },
    {
      "t": 2.9,
      "kind": "humanoid_state",
      "data": {
        "state": "Enum.HumanoidStateType.Freefall"
      }
    },
    {
      "t": 2.903,
      "kind": "jump_request",
      "data": []
    },
    {
      "t": 2.949,
      "kind": "movement",
      "data": {
        "isGrounded": false,
        "walkSpeed": 29,
        "jumpHeight": 7.2,
        "jumpPower": 50,
        "position": {
          "x": -377.384,
          "y": 291.975,
          "z": 685.261
        },
        "lookDirection": {
          "x": 1,
          "y": 0,
          "z": -0.013
        },
        "moveDirection": {
          "x": 1,
          "y": 0,
          "z": -0.017
        },
        "velocity": {
          "x": 28.996,
          "y": 37.621,
          "z": -0.506
        }
      }
    },
    {
      "t": 2.967,
      "kind": "key_up",
      "data": {
        "gameProcessed": false,
        "keyCode": "Enum.KeyCode.Space"
      }
    },
    {
      "t": 3.067,
      "kind": "movement",
      "data": {
        "isGrounded": false,
        "walkSpeed": 29,
        "jumpHeight": 7.2,
        "jumpPower": 50,
        "position": {
          "x": -374.002,
          "y": 294.981,
          "z": 685.176
        },
        "lookDirection": {
          "x": 1,
          "y": 0,
          "z": -0.022
        },
        "moveDirection": {
          "x": 0.999,
          "y": 0,
          "z": -0.035
        },
        "velocity": {
          "x": 28.982,
          "y": 14.731,
          "z": -1.012
        }
      }
    },
    {
      "t": 3.183,
      "kind": "movement",
      "data": {
        "isGrounded": false,
        "walkSpeed": 29,
        "jumpHeight": 7.2,
        "jumpPower": 50,
        "position": {
          "x": -370.741,
          "y": 295.351,
          "z": 685.062
        },
        "lookDirection": {
          "x": 1,
          "y": 0,
          "z": -0.03
        },
        "moveDirection": {
          "x": 0.999,
          "y": 0,
          "z": -0.035
        },
        "velocity": {
          "x": 28.982,
          "y": -7.342,
          "z": -1.012
        }
      }
    },
    {
      "t": 3.283,
      "kind": "movement",
      "data": {
        "isGrounded": false,
        "walkSpeed": 29,
        "jumpHeight": 7.2,
        "jumpPower": 50,
        "position": {
          "x": -367.846,
          "y": 293.595,
          "z": 684.908
        },
        "lookDirection": {
          "x": 0.999,
          "y": 0,
          "z": -0.045
        },
        "moveDirection": {
          "x": 0.998,
          "y": 0,
          "z": -0.07
        },
        "velocity": {
          "x": 28.929,
          "y": -26.962,
          "z": -2.023
        }
      }
    },
    {
      "t": 3.384,
      "kind": "humanoid_state",
      "data": {
        "state": "Enum.HumanoidStateType.Landed"
      }
    },
    {
      "t": 3.384,
      "kind": "movement",
      "data": {
        "isGrounded": true,
        "walkSpeed": 29,
        "jumpHeight": 7.2,
        "jumpPower": 50,
        "position": {
          "x": -364.84,
          "y": 290.655,
          "z": 684.614
        },
        "lookDirection": {
          "x": 0.997,
          "y": 0,
          "z": -0.078
        },
        "moveDirection": {
          "x": 0.993,
          "y": 0,
          "z": -0.122
        },
        "velocity": {
          "x": 28.786,
          "y": 25.665,
          "z": -3.508
        }
      }
    },
    {
      "t": 3.499,
      "kind": "movement",
      "data": {
        "isGrounded": true,
        "walkSpeed": 29,
        "jumpHeight": 7.2,
        "jumpPower": 50,
        "position": {
          "x": -362.268,
          "y": 291.335,
          "z": 684.221
        },
        "lookDirection": {
          "x": 0.992,
          "y": 0,
          "z": -0.127
        },
        "moveDirection": {
          "x": 0.986,
          "y": 0,
          "z": -0.165
        },
        "velocity": {
          "x": 26.309,
          "y": 4.374,
          "z": -4.382
        }
      }
    },
    {
      "t": 3.617,
      "kind": "movement",
      "data": {
        "isGrounded": true,
        "walkSpeed": 29,
        "jumpHeight": 7.2,
        "jumpPower": 50,
        "position": {
          "x": -359.706,
          "y": 291.533,
          "z": 683.792
        },
        "lookDirection": {
          "x": 0.988,
          "y": 0,
          "z": -0.152
        },
        "moveDirection": {
          "x": 0.986,
          "y": 0,
          "z": -0.165
        },
        "velocity": {
          "x": 20.269,
          "y": 3.438,
          "z": -3.385
        }
      }
    },
    {
      "t": 3.65,
      "kind": "key_down",
      "data": {
        "gameProcessed": false,
        "keyCode": "Enum.KeyCode.Space"
      }
    },
    {
      "t": 3.652,
      "kind": "jump_request",
      "data": []
    },
    {
      "t": 3.666,
      "kind": "humanoid_state",
      "data": {
        "state": "Enum.HumanoidStateType.Jumping"
      }
    },
    {
      "t": 3.669,
      "kind": "jump_request",
      "data": []
    },
    {
      "t": 3.682,
      "kind": "humanoid_state",
      "data": {
        "state": "Enum.HumanoidStateType.Freefall"
      }
    },
    {
      "t": 3.686,
      "kind": "jump_request",
      "data": []
    },
    {
      "t": 3.733,
      "kind": "movement",
      "data": {
        "isGrounded": false,
        "walkSpeed": 29,
        "jumpHeight": 7.2,
        "jumpPower": 50,
        "position": {
          "x": -356.815,
          "y": 295.313,
          "z": 683.339
        },
        "lookDirection": {
          "x": 0.988,
          "y": 0,
          "z": -0.154
        },
        "moveDirection": {
          "x": 0.991,
          "y": 0,
          "z": -0.131
        },
        "velocity": {
          "x": 28.75,
          "y": 37.621,
          "z": -3.799
        }
      }
    },
    {
      "t": 3.767,
      "kind": "key_up",
      "data": {
        "gameProcessed": false,
        "keyCode": "Enum.KeyCode.Space"
      }
    },
    {
      "t": 3.849,
      "kind": "movement",
      "data": {
        "isGrounded": false,
        "walkSpeed": 29,
        "jumpHeight": 7.2,
        "jumpPower": 50,
        "position": {
          "x": -353.452,
          "y": 298.319,
          "z": 682.964
        },
        "lookDirection": {
          "x": 0.992,
          "y": 0,
          "z": -0.125
        },
        "moveDirection": {
          "x": 0.995,
          "y": 0,
          "z": -0.105
        },
        "velocity": {
          "x": 28.841,
          "y": 14.731,
          "z": -3.031
        }
      }
    },
    {
      "t": 3.95,
      "kind": "movement",
      "data": {
        "isGrounded": false,
        "walkSpeed": 29,
        "jumpHeight": 7.2,
        "jumpPower": 50,
        "position": {
          "x": -350.568,
          "y": 298.771,
          "z": 682.661
        },
        "lookDirection": {
          "x": 0.994,
          "y": 0,
          "z": -0.113
        },
        "moveDirection": {
          "x": 0.995,
          "y": 0,
          "z": -0.105
        },
        "velocity": {
          "x": 28.841,
          "y": -4.889,
          "z": -3.031
        }
      }
    },
    {
      "t": 3.983,
      "kind": "humanoid_state",
      "data": {
        "state": "Enum.HumanoidStateType.Landed"
      }
    },
    {
      "t": 4.066,
      "kind": "movement",
      "data": {
        "isGrounded": true,
        "walkSpeed": 29,
        "jumpHeight": 7.2,
        "jumpPower": 50,
        "position": {
          "x": -347.435,
          "y": 298.07,
          "z": 682.18
        },
        "lookDirection": {
          "x": 0.989,
          "y": 0,
          "z": -0.146
        },
        "moveDirection": {
          "x": 0.978,
          "y": 0,
          "z": -0.208
        },
        "velocity": {
          "x": 24.539,
          "y": 11.753,
          "z": -5.174
        }
      }
    },
    {
      "t": 4.166,
      "kind": "movement",
      "data": {
        "isGrounded": false,
        "walkSpeed": 29,
        "jumpHeight": 7.2,
        "jumpPower": 50,
        "position": {
          "x": -344.704,
          "y": 300.279,
          "z": 681.421
        },
        "lookDirection": {
          "x": 0.975,
          "y": 0,
          "z": -0.223
        },
        "moveDirection": {
          "x": 0.943,
          "y": 0,
          "z": -0.334
        },
        "velocity": {
          "x": 27.592,
          "y": 14.096,
          "z": -8.911
        }
      }
    },
    {
      "t": 4.185,
      "kind": "key_down",
      "data": {
        "gameProcessed": false,
        "keyCode": "Enum.KeyCode.Space"
      }
    },
    {
      "t": 4.187,
      "kind": "jump_request",
      "data": []
    },
    {
      "t": 4.199,
      "kind": "humanoid_state",
      "data": {
        "state": "Enum.HumanoidStateType.Jumping"
      }
    },
    {
      "t": 4.203,
      "kind": "jump_request",
      "data": []
    },
    {
      "t": 4.234,
      "kind": "humanoid_state",
      "data": {
        "state": "Enum.HumanoidStateType.Freefall"
      }
    },
    {
      "t": 4.236,
      "kind": "jump_request",
      "data": []
    },
    {
      "t": 4.267,
      "kind": "movement",
      "data": {
        "isGrounded": false,
        "walkSpeed": 29,
        "jumpHeight": 7.2,
        "jumpPower": 50,
        "position": {
          "x": -342.04,
          "y": 305.142,
          "z": 680.419
        },
        "lookDirection": {
          "x": 0.951,
          "y": 0,
          "z": -0.31
        },
        "moveDirection": {
          "x": 0.921,
          "y": 0,
          "z": -0.391
        },
        "velocity": {
          "x": 26.698,
          "y": 43.343,
          "z": -11.322
        }
      }
    },
    {
      "t": 4.267,
      "kind": "key_up",
      "data": {
        "gameProcessed": false,
        "keyCode": "Enum.KeyCode.Space"
      }
    },
    {
      "t": 4.383,
      "kind": "movement",
      "data": {
        "isGrounded": false,
        "walkSpeed": 29,
        "jumpHeight": 7.2,
        "jumpPower": 50,
        "position": {
          "x": -339.105,
          "y": 308.73,
          "z": 678.996
        },
        "lookDirection": {
          "x": 0.919,
          "y": 0,
          "z": -0.394
        },
        "moveDirection": {
          "x": 0.87,
          "y": 0,
          "z": -0.492
        },
        "velocity": {
          "x": 25.251,
          "y": 21.271,
          "z": -14.261
        }
      }
    },
    {
      "t": 4.5,
      "kind": "movement",
      "data": {
        "isGrounded": false,
        "walkSpeed": 29,
        "jumpHeight": 7.2,
        "jumpPower": 50,
        "position": {
          "x": -336.116,
          "y": 309.819,
          "z": 677.168
        },
        "lookDirection": {
          "x": 0.876,
          "y": 0,
          "z": -0.482
        },
        "moveDirection": {
          "x": 0.834,
          "y": 0,
          "z": -0.552
        },
        "velocity": {
          "x": 24.185,
          "y": -2.437,
          "z": -16.003
        }
      }
    },
    {
      "t": 4.616,
      "kind": "movement",
      "data": {
        "isGrounded": false,
        "walkSpeed": 29,
        "jumpHeight": 7.2,
        "jumpPower": 50,
        "position": {
          "x": -333.57,
          "y": 308.257,
          "z": 675.134
        },
        "lookDirection": {
          "x": 0.816,
          "y": 0,
          "z": -0.578
        },
        "moveDirection": {
          "x": 0.731,
          "y": 0,
          "z": -0.682
        },
        "velocity": {
          "x": 21.219,
          "y": -24.509,
          "z": -19.767
        }
      }
    },
    {
      "t": 4.667,
      "kind": "humanoid_state",
      "data": {
        "state": "Enum.HumanoidStateType.Landed"
      }
    },
    {
      "t": 4.717,
      "kind": "movement",
      "data": {
        "isGrounded": true,
        "walkSpeed": 29,
        "jumpHeight": 7.2,
        "jumpPower": 50,
        "position": {
          "x": -331.644,
          "y": 304.837,
          "z": 672.816
        },
        "lookDirection": {
          "x": 0.71,
          "y": 0,
          "z": -0.705
        },
        "moveDirection": {
          "x": 0.566,
          "y": 0,
          "z": -0.824
        },
        "velocity": {
          "x": 16.499,
          "y": -9.457,
          "z": -23.827
        }
      }
    },
    {
      "t": 4.734,
      "kind": "key_down",
      "data": {
        "gameProcessed": false,
        "keyCode": "Enum.KeyCode.Space"
      }
    },
    {
      "t": 4.737,
      "kind": "jump_request",
      "data": []
    },
    {
      "t": 4.75,
      "kind": "humanoid_state",
      "data": {
        "state": "Enum.HumanoidStateType.Jumping"
      }
    },
    {
      "t": 4.753,
      "kind": "jump_request",
      "data": []
    },
    {
      "t": 4.818,
      "kind": "movement",
      "data": {
        "isGrounded": true,
        "walkSpeed": 29,
        "jumpHeight": 7.2,
        "jumpPower": 50,
        "position": {
          "x": -330.04,
          "y": 309.504,
          "z": 670.4
        },
        "lookDirection": {
          "x": 0.583,
          "y": -0.001,
          "z": -0.812
        },
        "moveDirection": {
          "x": 0.537,
          "y": 0,
          "z": -0.843
        },
        "velocity": {
          "x": 16.095,
          "y": 53.154,
          "z": -24.103
        }
      }
    },
    {
      "t": 4.832,
      "kind": "humanoid_state",
      "data": {
        "state": "Enum.HumanoidStateType.Freefall"
      }
    },
    {
      "t": 4.835,
      "kind": "jump_request",
      "data": []
    },
    {
      "t": 4.85,
      "kind": "key_up",
      "data": {
        "gameProcessed": false,
        "keyCode": "Enum.KeyCode.Space"
      }
    },
    {
      "t": 4.933,
      "kind": "movement",
      "data": {
        "isGrounded": false,
        "walkSpeed": 29,
        "jumpHeight": 7.2,
        "jumpPower": 50,
        "position": {
          "x": -328.288,
          "y": 314.196,
          "z": 667.648
        },
        "lookDirection": {
          "x": 0.551,
          "y": 0,
          "z": -0.834
        },
        "moveDirection": {
          "x": 0.537,
          "y": 0,
          "z": -0.843
        },
        "velocity": {
          "x": 15.582,
          "y": 31.082,
          "z": -24.458
        }
      }
    },
    {
      "t": 5.034,
      "kind": "movement",
      "data": {
        "isGrounded": false,
        "walkSpeed": 29,
        "jumpHeight": 7.2,
        "jumpPower": 50,
        "position": {
          "x": -326.636,
          "y": 316.327,
          "z": 665.119
        },
        "lookDirection": {
          "x": 0.549,
          "y": 0,
          "z": -0.836
        },
        "moveDirection": {
          "x": 0.552,
          "y": 0,
          "z": -0.834
        },
        "velocity": {
          "x": 16.006,
          "y": 10.644,
          "z": -24.183
        }
      }
    },
    {
      "t": 5.136,
      "kind": "movement",
      "data": {
        "isGrounded": false,
        "walkSpeed": 29,
        "jumpHeight": 7.2,
        "jumpPower": 50,
        "position": {
          "x": -325.036,
          "y": 316.37,
          "z": 662.701
        },
        "lookDirection": {
          "x": 0.551,
          "y": 0,
          "z": -0.835
        },
        "moveDirection": {
          "x": 0.552,
          "y": 0,
          "z": -0.834
        },
        "velocity": {
          "x": 16.006,
          "y": -8.976,
          "z": -24.183
        }
      }
    },
    {
      "t": 5.199,
      "kind": "humanoid_state",
      "data": {
        "state": "Enum.HumanoidStateType.Landed"
      }
    },
    {
      "t": 5.251,
      "kind": "movement",
      "data": {
        "isGrounded": true,
        "walkSpeed": 29,
        "jumpHeight": 7.2,
        "jumpPower": 50,
        "position": {
          "x": -323.303,
          "y": 315.197,
          "z": 660.072
        },
        "lookDirection": {
          "x": 0.55,
          "y": 0,
          "z": -0.835
        },
        "moveDirection": {
          "x": 0.545,
          "y": 0,
          "z": -0.839
        },
        "velocity": {
          "x": 14.315,
          "y": -17.601,
          "z": -22.037
        }
      }
    },
    {
      "t": 5.367,
      "kind": "movement",
      "data": {
        "isGrounded": false,
        "walkSpeed": 29,
        "jumpHeight": 7.2,
        "jumpPower": 50,
        "position": {
          "x": -321.565,
          "y": 313.878,
          "z": 657.309
        },
        "lookDirection": {
          "x": 0.54,
          "y": 0,
          "z": -0.841
        },
        "moveDirection": {
          "x": 0.53,
          "y": 0,
          "z": -0.848
        },
        "velocity": {
          "x": 12.847,
          "y": 20.285,
          "z": -20.546
        }
      }
    },
    {
      "t": 5.468,
      "kind": "movement",
      "data": {
        "isGrounded": true,
        "walkSpeed": 29,
        "jumpHeight": 7.2,
        "jumpPower": 50,
        "position": {
          "x": -320.387,
          "y": 318.561,
          "z": 655.423
        },
        "lookDirection": {
          "x": 0.535,
          "y": 0,
          "z": -0.845
        },
        "moveDirection": {
          "x": 0.53,
          "y": 0,
          "z": -0.848
        },
        "velocity": {
          "x": 11.03,
          "y": 24.997,
          "z": -17.645
        }
      }
    },
    {
      "t": 5.583,
      "kind": "movement",
      "data": {
        "isGrounded": true,
        "walkSpeed": 29,
        "jumpHeight": 7.2,
        "jumpPower": 50,
        "position": {
          "x": -318.988,
          "y": 320.874,
          "z": 653.231
        },
        "lookDirection": {
          "x": 0.537,
          "y": 0,
          "z": -0.844
        },
        "moveDirection": {
          "x": 0.545,
          "y": 0,
          "z": -0.839
        },
        "velocity": {
          "x": 15.225,
          "y": 22.8,
          "z": -23.453
        }
      }
    },
    {
      "t": 5.685,
      "kind": "movement",
      "data": {
        "isGrounded": false,
        "walkSpeed": 29,
        "jumpHeight": 7.2,
        "jumpPower": 50,
        "position": {
          "x": -317.429,
          "y": 323.454,
          "z": 650.892
        },
        "lookDirection": {
          "x": 0.55,
          "y": 0,
          "z": -0.835
        },
        "moveDirection": {
          "x": 0.574,
          "y": 0,
          "z": -0.819
        },
        "velocity": {
          "x": 14.458,
          "y": 24.806,
          "z": -20.905
        }
      }
    },
    {
      "t": 5.785,
      "kind": "humanoid_state",
      "data": {
        "state": "Enum.HumanoidStateType.Freefall"
      }
    },
    {
      "t": 5.786,
      "kind": "movement",
      "data": {
        "isGrounded": false,
        "walkSpeed": 29,
        "jumpHeight": 7.2,
        "jumpPower": 50,
        "position": {
          "x": -315.579,
          "y": 324.913,
          "z": 648.719
        },
        "lookDirection": {
          "x": 0.613,
          "y": 0,
          "z": -0.79
        },
        "moveDirection": {
          "x": 0.695,
          "y": 0,
          "z": -0.719
        },
        "velocity": {
          "x": 20.14,
          "y": 5.186,
          "z": -20.865
        }
      }
    },
    {
      "t": 5.787,
      "kind": "key_down",
      "data": {
        "gameProcessed": false,
        "keyCode": "Enum.KeyCode.Space"
      }
    },
    {
      "t": 5.789,
      "kind": "jump_request",
      "data": []
    },
    {
      "t": 5.883,
      "kind": "humanoid_state",
      "data": {
        "state": "Enum.HumanoidStateType.Landed"
      }
    },
    {
      "t": 5.884,
      "kind": "key_up",
      "data": {
        "gameProcessed": false,
        "keyCode": "Enum.KeyCode.Space"
      }
    },
    {
      "t": 5.9,
      "kind": "movement",
      "data": {
        "isGrounded": true,
        "walkSpeed": 29,
        "jumpHeight": 7.2,
        "jumpPower": 50,
        "position": {
          "x": -313.311,
          "y": 325.235,
          "z": 646.375
        },
        "lookDirection": {
          "x": 0.676,
          "y": 0,
          "z": -0.737
        },
        "moveDirection": {
          "x": 0.707,
          "y": 0,
          "z": -0.707
        },
        "velocity": {
          "x": 19.287,
          "y": 15.164,
          "z": -21.206
        }
      }
    },
    {
      "t": 6,
      "kind": "movement",
      "data": {
        "isGrounded": true,
        "walkSpeed": 29,
        "jumpHeight": 7.2,
        "jumpPower": 50,
        "position": {
          "x": -311.487,
          "y": 325.521,
          "z": 644.282
        },
        "lookDirection": {
          "x": 0.69,
          "y": 0,
          "z": -0.724
        },
        "moveDirection": {
          "x": 0.682,
          "y": 0,
          "z": -0.731
        },
        "velocity": {
          "x": 17.801,
          "y": -3.582,
          "z": -20.622
        }
      }
    },
    {
      "t": 6.1,
      "kind": "key_up",
      "data": {
        "gameProcessed": false,
        "keyCode": "Enum.KeyCode.W"
      }
    },
    {
      "t": 6.118,
      "kind": "movement",
      "data": {
        "isGrounded": true,
        "walkSpeed": 29,
        "jumpHeight": 7.2,
        "jumpPower": 50,
        "position": {
          "x": -309.332,
          "y": 325.718,
          "z": 641.892
        },
        "lookDirection": {
          "x": 0.687,
          "y": 0,
          "z": -0.726
        },
        "moveDirection": {
          "x": 0,
          "y": 0,
          "z": 0
        },
        "velocity": {
          "x": 12.118,
          "y": -4.535,
          "z": -13.673
        }
      }
    },
    {
      "t": 6.234,
      "kind": "movement",
      "data": {
        "isGrounded": true,
        "walkSpeed": 29,
        "jumpHeight": 7.2,
        "jumpPower": 50,
        "position": {
          "x": -308.94,
          "y": 325.459,
          "z": 641.436
        },
        "lookDirection": {
          "x": 0.698,
          "y": 0,
          "z": -0.716
        },
        "moveDirection": {
          "x": 0,
          "y": 0,
          "z": 0
        },
        "velocity": {
          "x": 1.882,
          "y": -0.026,
          "z": -2.628
        }
      }
    },
    {
      "t": 6.27,
      "kind": "key_down",
      "data": {
        "gameProcessed": false,
        "keyCode": "Enum.KeyCode.W"
      }
    },
    {
      "t": 6.351,
      "kind": "movement",
      "data": {
        "isGrounded": true,
        "walkSpeed": 29,
        "jumpHeight": 7.2,
        "jumpPower": 50,
        "position": {
          "x": -308.085,
          "y": 325.157,
          "z": 640.491
        },
        "lookDirection": {
          "x": 0.691,
          "y": 0,
          "z": -0.723
        },
        "moveDirection": {
          "x": 0.682,
          "y": 0,
          "z": -0.731
        },
        "velocity": {
          "x": 17.588,
          "y": 10.059,
          "z": -18.386
        }
      }
    },
    {
      "t": 6.435,
      "kind": "key_down",
      "data": {
        "gameProcessed": false,
        "keyCode": "Enum.KeyCode.Space"
      }
    },
    {
      "t": 6.44,
      "kind": "jump_request",
      "data": []
    },
    {
      "t": 6.45,
      "kind": "humanoid_state",
      "data": {
        "state": "Enum.HumanoidStateType.Jumping"
      }
    },
    {
      "t": 6.453,
      "kind": "movement",
      "data": {
        "isGrounded": false,
        "walkSpeed": 29,
        "jumpHeight": 7.2,
        "jumpPower": 50,
        "position": {
          "x": -306.344,
          "y": 326.716,
          "z": 638.553
        },
        "lookDirection": {
          "x": 0.679,
          "y": 0,
          "z": -0.734
        },
        "moveDirection": {
          "x": 0.682,
          "y": 0,
          "z": -0.731
        },
        "velocity": {
          "x": 18.619,
          "y": 50.701,
          "z": -19.964
        }
      }
    },
    {
      "t": 6.456,
      "kind": "jump_request",
      "data": []
    },
    {
      "t": 6.467,
      "kind": "humanoid_state",
      "data": {
        "state": "Enum.HumanoidStateType.Freefall"
      }
    },
    {
      "t": 6.47,
      "kind": "jump_request",
      "data": []
    },
    {
      "t": 6.552,
      "kind": "key_up",
      "data": {
        "gameProcessed": false,
        "keyCode": "Enum.KeyCode.Space"
      }
    },
    {
      "t": 6.567,
      "kind": "movement",
      "data": {
        "isGrounded": false,
        "walkSpeed": 29,
        "jumpHeight": 7.2,
        "jumpPower": 50,
        "position": {
          "x": -304.02,
          "y": 331.36,
          "z": 635.941
        },
        "lookDirection": {
          "x": 0.669,
          "y": 0,
          "z": -0.743
        },
        "moveDirection": {
          "x": 0.656,
          "y": 0,
          "z": -0.755
        },
        "velocity": {
          "x": 19.026,
          "y": 26.993,
          "z": -21.887
        }
      }
    },
    {
      "t": 6.684,
      "kind": "movement",
      "data": {
        "isGrounded": false,
        "walkSpeed": 29,
        "jumpHeight": 7.2,
        "jumpPower": 50,
        "position": {
          "x": -303.347,
          "y": 333.71,
          "z": 635.245
        },
        "lookDirection": {
          "x": 0.7,
          "y": 0,
          "z": -0.714
        },
        "moveDirection": {
          "x": 0.616,
          "y": 0,
          "z": -0.788
        },
        "velocity": {
          "x": 0.004,
          "y": 20.299,
          "z": -0.006
        }
      }
    },
    {
      "t": 6.685,
      "kind": "key_up",
      "data": {
        "gameProcessed": false,
        "keyCode": "Enum.KeyCode.W"
      }
    },
    {
      "t": 6.785,
      "kind": "movement",
      "data": {
        "isGrounded": false,
        "walkSpeed": 29,
        "jumpHeight": 7.2,
        "jumpPower": 50,
        "position": {
          "x": -303.347,
          "y": 333.76,
          "z": 635.245
        },
        "lookDirection": {
          "x": 0.7,
          "y": 0,
          "z": -0.714
        },
        "moveDirection": {
          "x": 0,
          "y": 0,
          "z": 0
        },
        "velocity": {
          "x": 0,
          "y": 0,
          "z": 0
        }
      }
    },
    {
      "t": 6.901,
      "kind": "movement",
      "data": {
        "isGrounded": false,
        "walkSpeed": 29,
        "jumpHeight": 7.2,
        "jumpPower": 50,
        "position": {
          "x": -303.347,
          "y": 333.76,
          "z": 635.245
        },
        "lookDirection": {
          "x": 0.7,
          "y": 0,
          "z": -0.714
        },
        "moveDirection": {
          "x": 0,
          "y": 0,
          "z": 0
        },
        "velocity": {
          "x": 0,
          "y": 0,
          "z": 0
        }
      }
    },
    {
      "t": 6.999,
      "kind": "movement",
      "data": {
        "isGrounded": false,
        "walkSpeed": 29,
        "jumpHeight": 7.2,
        "jumpPower": 50,
        "position": {
          "x": -303.347,
          "y": 333.76,
          "z": 635.245
        },
        "lookDirection": {
          "x": 0.7,
          "y": 0,
          "z": -0.714
        },
        "moveDirection": {
          "x": 0,
          "y": 0,
          "z": 0
        },
        "velocity": {
          "x": 0,
          "y": 0,
          "z": 0
        }
      }
    },
    {
      "t": 7.034,
      "kind": "key_down",
      "data": {
        "gameProcessed": false,
        "keyCode": "Enum.KeyCode.W"
      }
    },
    {
      "t": 7.099,
      "kind": "humanoid_state",
      "data": {
        "state": "Enum.HumanoidStateType.Freefall"
      }
    },
    {
      "t": 7.1,
      "kind": "movement",
      "data": {
        "isGrounded": false,
        "walkSpeed": 29,
        "jumpHeight": 7.2,
        "jumpPower": 50,
        "position": {
          "x": -303.408,
          "y": 334.883,
          "z": 635.188
        },
        "lookDirection": {
          "x": 0.494,
          "y": -0.001,
          "z": -0.869
        },
        "moveDirection": {
          "x": -0.743,
          "y": 0,
          "z": -0.669
        },
        "velocity": {
          "x": -3.018,
          "y": 14.57,
          "z": -2.876
        }
      }
    },
    {
      "t": 7.2,
      "kind": "humanoid_state",
      "data": {
        "state": "Enum.HumanoidStateType.Landed"
      }
    },
    {
      "t": 7.201,
      "kind": "movement",
      "data": {
        "isGrounded": true,
        "walkSpeed": 29,
        "jumpHeight": 7.2,
        "jumpPower": 50,
        "position": {
          "x": -304.363,
          "y": 336.066,
          "z": 634.43
        },
        "lookDirection": {
          "x": -0.249,
          "y": 0,
          "z": -0.969
        },
        "moveDirection": {
          "x": -0.793,
          "y": 0,
          "z": -0.609
        },
        "velocity": {
          "x": -15.731,
          "y": 48.823,
          "z": -12.426
        }
      }
    },
    {
      "t": 7.316,
      "kind": "humanoid_state",
      "data": {
        "state": "Enum.HumanoidStateType.Freefall"
      }
    },
    {
      "t": 7.317,
      "kind": "movement",
      "data": {
        "isGrounded": false,
        "walkSpeed": 29,
        "jumpHeight": 7.2,
        "jumpPower": 50,
        "position": {
          "x": -306.214,
          "y": 341.327,
          "z": 632.989
        },
        "lookDirection": {
          "x": -0.429,
          "y": 0,
          "z": -0.903
        },
        "moveDirection": {
          "x": -0.793,
          "y": 0,
          "z": -0.609
        },
        "velocity": {
          "x": -13.242,
          "y": 31.73,
          "z": -10.316
        }
      }
    },
    {
      "t": 7.417,
      "kind": "movement",
      "data": {
        "isGrounded": false,
        "walkSpeed": 29,
        "jumpHeight": 7.2,
        "jumpPower": 50,
        "position": {
          "x": -308.129,
          "y": 343.478,
          "z": 631.531
        },
        "lookDirection": {
          "x": -0.663,
          "y": 0,
          "z": -0.749
        },
        "moveDirection": {
          "x": -0.793,
          "y": 0,
          "z": -0.609
        },
        "velocity": {
          "x": -23.002,
          "y": 12.11,
          "z": -17.65
        }
      }
    },
    {
      "t": 7.533,
      "kind": "movement",
      "data": {
        "isGrounded": false,
        "walkSpeed": 29,
        "jumpHeight": 7.2,
        "jumpPower": 50,
        "position": {
          "x": -308.288,
          "y": 345.644,
          "z": 631.452
        },
        "lookDirection": {
          "x": -0.736,
          "y": 0,
          "z": -0.677
        },
        "moveDirection": {
          "x": -0.793,
          "y": 0,
          "z": -0.609
        },
        "velocity": {
          "x": -0.009,
          "y": 20.297,
          "z": 0.012
        }
      }
    },
    {
      "t": 7.634,
      "kind": "movement",
      "data": {
        "isGrounded": false,
        "walkSpeed": 29,
        "jumpHeight": 7.2,
        "jumpPower": 50,
        "position": {
          "x": -308.289,
          "y": 347.759,
          "z": 631.452
        },
        "lookDirection": {
          "x": -0.736,
          "y": 0,
          "z": -0.677
        },
        "moveDirection": {
          "x": -0.814,
          "y": 0,
          "z": -0.581
        },
        "velocity": {
          "x": 0,
          "y": 20.3,
          "z": 0
        }
      }
    },
    {
      "t": 7.716,
      "kind": "humanoid_state",
      "data": {
        "state": "Enum.HumanoidStateType.Freefall"
      }
    },
    {
      "t": 7.749,
      "kind": "movement",
      "data": {
        "isGrounded": false,
        "walkSpeed": 29,
        "jumpHeight": 7.2,
        "jumpPower": 50,
        "position": {
          "x": -308.595,
          "y": 349.58,
          "z": 631.307
        },
        "lookDirection": {
          "x": -0.813,
          "y": 0,
          "z": -0.582
        },
        "moveDirection": {
          "x": -0.91,
          "y": 0,
          "z": -0.415
        },
        "velocity": {
          "x": -8.59,
          "y": 7.22,
          "z": -4.126
        }
      }
    },
    {
      "t": 7.818,
      "kind": "humanoid_state",
      "data": {
        "state": "Enum.HumanoidStateType.Landed"
      }
    },
    {
      "t": 7.834,
      "kind": "key_down",
      "data": {
        "gameProcessed": false,
        "keyCode": "Enum.KeyCode.Space"
      }
    },
    {
      "t": 7.836,
      "kind": "jump_request",
      "data": []
    },
    {
      "t": 7.852,
      "kind": "movement",
      "data": {
        "isGrounded": true,
        "walkSpeed": 29,
        "jumpHeight": 7.2,
        "jumpPower": 50,
        "position": {
          "x": -310.186,
          "y": 351.845,
          "z": 630.576
        },
        "lookDirection": {
          "x": -0.876,
          "y": 0,
          "z": -0.482
        },
        "moveDirection": {
          "x": -0.91,
          "y": 0,
          "z": -0.415
        },
        "velocity": {
          "x": -16.608,
          "y": 37.562,
          "z": -7.613
        }
      }
    },
    {
      "t": 7.853,
      "kind": "jump_request",
      "data": []
    },
    {
      "t": 7.867,
      "kind": "humanoid_state",
      "data": {
        "state": "Enum.HumanoidStateType.Jumping"
      }
    },
    {
      "t": 7.869,
      "kind": "jump_request",
      "data": []
    },
    {
      "t": 7.883,
      "kind": "humanoid_state",
      "data": {
        "state": "Enum.HumanoidStateType.Freefall"
      }
    },
    {
      "t": 7.886,
      "kind": "jump_request",
      "data": []
    },
    {
      "t": 7.918,
      "kind": "key_up",
      "data": {
        "gameProcessed": false,
        "keyCode": "Enum.KeyCode.Space"
      }
    },
    {
      "t": 7.968,
      "kind": "movement",
      "data": {
        "isGrounded": false,
        "walkSpeed": 29,
        "jumpHeight": 7.2,
        "jumpPower": 50,
        "position": {
          "x": -312.752,
          "y": 357.024,
          "z": 629.398
        },
        "lookDirection": {
          "x": -0.899,
          "y": 0,
          "z": -0.439
        },
        "moveDirection": {
          "x": -0.906,
          "y": 0,
          "z": -0.423
        },
        "velocity": {
          "x": -26.282,
          "y": 33.533,
          "z": -12.256
        }
      }
    },
    {
      "t": 8.082,
      "kind": "movement",
      "data": {
        "isGrounded": true,
        "walkSpeed": 29,
        "jumpHeight": 7.2,
        "jumpPower": 50,
        "position": {
          "x": -315.683,
          "y": 359.509,
          "z": 627.967
        },
        "lookDirection": {
          "x": -0.898,
          "y": 0,
          "z": -0.44
        },
        "moveDirection": {
          "x": -0.891,
          "y": 0,
          "z": -0.454
        },
        "velocity": {
          "x": -25.845,
          "y": 11.461,
          "z": -13.154
        }
      }
    },
    {
      "t": 8.183,
      "kind": "movement",
      "data": {
        "isGrounded": false,
        "walkSpeed": 29,
        "jumpHeight": 7.2,
        "jumpPower": 50,
        "position": {
          "x": -318.235,
          "y": 359.633,
          "z": 626.59
        },
        "lookDirection": {
          "x": -0.887,
          "y": 0,
          "z": -0.461
        },
        "moveDirection": {
          "x": -0.862,
          "y": 0,
          "z": -0.508
        },
        "velocity": {
          "x": -25.007,
          "y": -8.159,
          "z": -14.684
        }
      }
    },
    {
      "t": 8.268,
      "kind": "key_down",
      "data": {
        "gameProcessed": false,
        "keyCode": "Enum.KeyCode.Space"
      }
    },
    {
      "t": 8.27,
      "kind": "jump_request",
      "data": []
    },
    {
      "t": 8.284,
      "kind": "movement",
      "data": {
        "isGrounded": false,
        "walkSpeed": 29,
        "jumpHeight": 7.2,
        "jumpPower": 50,
        "position": {
          "x": -320.654,
          "y": 357.796,
          "z": 624.992
        },
        "lookDirection": {
          "x": -0.857,
          "y": 0,
          "z": -0.516
        },
        "moveDirection": {
          "x": -0.824,
          "y": 0,
          "z": -0.566
        },
        "velocity": {
          "x": -23.907,
          "y": -27.779,
          "z": -16.415
        }
      }
    },
    {
      "t": 8.383,
      "kind": "key_up",
      "data": {
        "gameProcessed": false,
        "keyCode": "Enum.KeyCode.Space"
      }
    },
    {
      "t": 8.401,
      "kind": "movement",
      "data": {
        "isGrounded": false,
        "walkSpeed": 29,
        "jumpHeight": 7.2,
        "jumpPower": 50,
        "position": {
          "x": -320.393,
          "y": 354.963,
          "z": 625.326
        },
        "lookDirection": {
          "x": -0.912,
          "y": 0.003,
          "z": -0.41
        },
        "moveDirection": {
          "x": -0.824,
          "y": 0,
          "z": -0.566
        },
        "velocity": {
          "x": 6.453,
          "y": -28.6,
          "z": 4.175
        }
      }
    },
    {
      "t": 8.517,
      "kind": "movement",
      "data": {
        "isGrounded": false,
        "walkSpeed": 29,
        "jumpHeight": 7.2,
        "jumpPower": 50,
        "position": {
          "x": -320.52,
          "y": 350.025,
          "z": 625.238
        },
        "lookDirection": {
          "x": -0.868,
          "y": 0,
          "z": -0.496
        },
        "moveDirection": {
          "x": -0.853,
          "y": 0,
          "z": -0.522
        },
        "velocity": {
          "x": -8.132,
          "y": -52.308,
          "z": -5.088
        }
      }
    },
    {
      "t": 8.633,
      "kind": "movement",
      "data": {
        "isGrounded": false,
        "walkSpeed": 29,
        "jumpHeight": 7.2,
        "jumpPower": 50,
        "position": {
          "x": -322.237,
          "y": 342.853,
          "z": 624.178
        },
        "lookDirection": {
          "x": -0.858,
          "y": 0,
          "z": -0.513
        },
        "moveDirection": {
          "x": -0.853,
          "y": 0,
          "z": -0.522
        },
        "velocity": {
          "x": -21.887,
          "y": -74.38,
          "z": -13.43
        }
      }
    },
    {
      "t": 8.749,
      "kind": "movement",
      "data": {
        "isGrounded": false,
        "walkSpeed": 29,
        "jumpHeight": 7.2,
        "jumpPower": 50,
        "position": {
          "x": -325.089,
          "y": 332.793,
          "z": 622.421
        },
        "lookDirection": {
          "x": -0.854,
          "y": 0,
          "z": -0.521
        },
        "moveDirection": {
          "x": -0.848,
          "y": 0,
          "z": -0.53
        },
        "velocity": {
          "x": -24.593,
          "y": -97.27,
          "z": -15.368
        }
      }
    },
    {
      "t": 8.85,
      "kind": "movement",
      "data": {
        "isGrounded": false,
        "walkSpeed": 29,
        "jumpHeight": 7.2,
        "jumpPower": 50,
        "position": {
          "x": -327.549,
          "y": 322.044,
          "z": 620.884
        },
        "lookDirection": {
          "x": -0.85,
          "y": 0,
          "z": -0.526
        },
        "moveDirection": {
          "x": -0.848,
          "y": 0,
          "z": -0.53
        },
        "velocity": {
          "x": -24.593,
          "y": -116.89,
          "z": -15.368
        }
      }
    },
    {
      "t": 8.9,
      "kind": "key_up",
      "data": {
        "gameProcessed": false,
        "keyCode": "Enum.KeyCode.W"
      }
    },
    {
      "t": 8.95,
      "kind": "movement",
      "data": {
        "isGrounded": false,
        "walkSpeed": 29,
        "jumpHeight": 7.2,
        "jumpPower": 50,
        "position": {
          "x": -329.844,
          "y": 309.333,
          "z": 619.45
        },
        "lookDirection": {
          "x": -0.849,
          "y": 0,
          "z": -0.528
        },
        "moveDirection": {
          "x": 0,
          "y": 0,
          "z": 0
        },
        "velocity": {
          "x": -18.53,
          "y": -136.51,
          "z": -11.579
        }
      }
    },
    {
      "t": 9.066,
      "kind": "movement",
      "data": {
        "isGrounded": false,
        "walkSpeed": 29,
        "jumpHeight": 7.2,
        "jumpPower": 50,
        "position": {
          "x": -331.151,
          "y": 292.024,
          "z": 618.633
        },
        "lookDirection": {
          "x": -0.849,
          "y": 0,
          "z": -0.528
        },
        "moveDirection": {
          "x": 0,
          "y": 0,
          "z": 0
        },
        "velocity": {
          "x": -4.382,
          "y": -159.4,
          "z": -2.738
        }
      }
    },
    {
      "t": 9.166,
      "kind": "movement",
      "data": {
        "isGrounded": false,
        "walkSpeed": 29,
        "jumpHeight": 7.2,
        "jumpPower": 50,
        "position": {
          "x": -331.222,
          "y": 275.062,
          "z": 618.589
        },
        "lookDirection": {
          "x": -0.849,
          "y": 0,
          "z": -0.528
        },
        "moveDirection": {
          "x": 0,
          "y": 0,
          "z": 0
        },
        "velocity": {
          "x": 0,
          "y": -179.02,
          "z": 0
        }
      }
    },
    {
      "t": 9.267,
      "kind": "movement",
      "data": {
        "isGrounded": false,
        "walkSpeed": 29,
        "jumpHeight": 7.2,
        "jumpPower": 50,
        "position": {
          "x": -331.222,
          "y": 255.307,
          "z": 618.589
        },
        "lookDirection": {
          "x": -0.849,
          "y": 0,
          "z": -0.528
        },
        "moveDirection": {
          "x": 0,
          "y": 0,
          "z": 0
        },
        "velocity": {
          "x": 0,
          "y": -199.458,
          "z": 0
        }
      }
    },
    {
      "t": 9.384,
      "kind": "movement",
      "data": {
        "isGrounded": false,
        "walkSpeed": 29,
        "jumpHeight": 7.2,
        "jumpPower": 50,
        "position": {
          "x": -331.222,
          "y": 231.58,
          "z": 618.589
        },
        "lookDirection": {
          "x": -0.849,
          "y": 0,
          "z": -0.528
        },
        "moveDirection": {
          "x": 0,
          "y": 0,
          "z": 0
        },
        "velocity": {
          "x": 0,
          "y": -221.53,
          "z": 0
        }
      }
    },
    {
      "t": 9.499,
      "kind": "humanoid_state",
      "data": {
        "state": "Enum.HumanoidStateType.Landed"
      }
    },
    {
      "t": 9.5,
      "kind": "movement",
      "data": {
        "isGrounded": true,
        "walkSpeed": 29,
        "jumpHeight": 7.2,
        "jumpPower": 50,
        "position": {
          "x": -331.222,
          "y": 205.695,
          "z": 618.589
        },
        "lookDirection": {
          "x": -0.849,
          "y": 0,
          "z": -0.528
        },
        "moveDirection": {
          "x": 0,
          "y": 0,
          "z": 0
        },
        "velocity": {
          "x": 0,
          "y": -46.404,
          "z": 0
        }
      }
    },
    {
      "t": 9.616,
      "kind": "movement",
      "data": {
        "isGrounded": true,
        "walkSpeed": 29,
        "jumpHeight": 7.2,
        "jumpPower": 50,
        "position": {
          "x": -331.222,
          "y": 207.319,
          "z": 618.589
        },
        "lookDirection": {
          "x": -0.849,
          "y": 0,
          "z": -0.528
        },
        "moveDirection": {
          "x": 0,
          "y": 0,
          "z": 0
        },
        "velocity": {
          "x": 0,
          "y": 1.272,
          "z": 0
        }
      }
    },
    {
      "t": 9.733,
      "kind": "movement",
      "data": {
        "isGrounded": true,
        "walkSpeed": 29,
        "jumpHeight": 7.2,
        "jumpPower": 50,
        "position": {
          "x": -433,
          "y": 250.114,
          "z": 793
        },
        "lookDirection": {
          "x": 1,
          "y": 0,
          "z": 0
        },
        "moveDirection": {
          "x": 0,
          "y": 0,
          "z": 0
        },
        "velocity": {
          "x": 0,
          "y": 0.316,
          "z": 0
        }
      }
    },
    {
      "t": 9.834,
      "kind": "movement",
      "data": {
        "isGrounded": true,
        "walkSpeed": 29,
        "jumpHeight": 7.2,
        "jumpPower": 50,
        "position": {
          "x": -433,
          "y": 250.122,
          "z": 793
        },
        "lookDirection": {
          "x": 1,
          "y": 0,
          "z": 0
        },
        "moveDirection": {
          "x": 0,
          "y": 0,
          "z": 0
        },
        "velocity": {
          "x": 0,
          "y": 0.008,
          "z": 0
        }
      }
    }
  ]
}